{
  "id": "cacador",
  "name": "Caçador",
  "hit_points": {
    "initial": 16,
    "per_level": 4
  },
  "mana_points": {
    "per_level": 4
  },
  "skills": {
    "mandatory": [
      {
        "choose_one": [
          { "name": "Luta", "attribute": "For" },
          { "name": "Pontaria", "attribute": "Des" }
        ]
      },
      { "name": "Sobrevivência", "attribute": "Sab" }
    ],
    "choose_amount": 6,
    "choose_from": [
      { "name": "Adestramento", "attribute": "Car" },
      { "name": "Atletismo", "attribute": "For" },
      { "name": "Cavalgar", "attribute": "Des" },
      { "name": "Cura", "attribute": "Sab" },
      { "name": "Fortitude", "attribute": "Con" },
      { "name": "Furtividade", "attribute": "Des" },
      { "name": "Iniciativa", "attribute": "Des" },
      { "name": "Investigação", "attribute": "Int" },
      { "name": "Luta", "attribute": "For" },
      { "name": "Ofício", "attribute": "Int" },
      { "name": "Percepção", "attribute": "Sab" },
      { "name": "Pontaria", "attribute": "Des" },
      { "name": "Reflexos", "attribute": "Des" }
    ]
  },
  "proficiencies": {
    "weapons": ["marciais"],
    "armors": [],
    "shields": true
  },
  "abilities": [
    "marca_da_presa",
    "rastreador",
    "explorador",
    "caminho_do_explorador",
    "mestre_cacador"
  ],
  "powers": [
    "ambidestria",
    "armadilha_arataca",
    "armadilha_espinhos",
    "armadilha_laco",
    "armadilha_rede",
    "arqueiro",
    "aumento_de_atributo",
    "bote",
    "camuflagem",
    "chuva_de_laminas",
    "companheiro_animal",
    "elo_com_a_natureza",
    "emboscar",
    "empatia_selvagem",
    "ervas_curativas",
    "escaramuca",
    "escaramuca_superior",
    "espreitar",
    "impeto",
    "inimigo_de_criatura",
    "olho_do_falcao",
    "ponto_fraco"
  ],
  "progression": [
    { "level": 1, "abilities": ["marca_da_presa", "rastreador"] },
    { "level": 2, "abilities": ["poder_de_cacador"] },
    { "level": 3, "abilities": ["explorador", "poder_de_cacador"] },
    { "level": 4, "abilities": ["poder_de_cacador"] },
    { "level": 5, "abilities": ["caminho_do_explorador", "poder_de_cacador"] },
    { "level": 6, "abilities": ["poder_de_cacador"] },
    { "level": 7, "abilities": ["poder_de_cacador"] },
    { "level": 8, "abilities": ["poder_de_cacador"] },
    { "level": 9, "abilities": ["poder_de_cacador"] },
    { "level": 10, "abilities": ["poder_de_cacador"] },
    { "level": 11, "abilities": ["poder_de_cacador"] },
    { "level": 12, "abilities": ["poder_de_cacador"] },
    { "level": 13, "abilities": ["poder_de_cacador"] },
    { "level": 14, "abilities": ["poder_de_cacador"] },
    { "level": 15, "abilities": ["poder_de_cacador"] },
    { "level": 16, "abilities": ["poder_de_cacador"] },
    { "level": 17, "abilities": ["poder_de_cacador"] },
    { "level": 18, "abilities": ["poder_de_cacador"] },
    { "level": 19, "abilities": ["poder_de_cacador"] },
    { "level": 20, "abilities": ["mestre_cacador", "poder_de_cacador"] }
  ]
}
